clgraph/__init__.py
clgraph/agent.py
clgraph/column.py
clgraph/diff.py
clgraph/export.py
clgraph/lineage_builder.py
clgraph/metadata_parser.py
clgraph/models.py
clgraph/multi_query.py
clgraph/parser.py
clgraph/pipeline.py
clgraph/py.typed
clgraph/query_parser.py
clgraph/table.py
clgraph/visualizations.py
clgraph/mcp/__init__.py
clgraph/mcp/__main__.py
clgraph/mcp/server.py
clgraph/tools/__init__.py
clgraph/tools/base.py
clgraph/tools/context.py
clgraph/tools/governance.py
clgraph/tools/lineage.py
clgraph/tools/schema.py
clgraph/tools/sql.py
clgraph-0.0.3.dist-info/METADATA
clgraph-0.0.3.dist-info/WHEEL
clgraph-0.0.3.dist-info/licenses/LICENSE
clgraph-0.0.3.dist-info/RECORD
