Metadata-Version: 2.4
Name: clgraph
Version: 0.0.3
Summary: Column lineage and pipeline dependency analysis for SQL
Project-URL: Homepage, https://github.com/mingjerli/clgraph
Project-URL: Documentation, https://github.com/mingjerli/clgraph#readme
Project-URL: Repository, https://github.com/mingjerli/clgraph
Project-URL: Issues, https://github.com/mingjerli/clgraph/issues
Author-email: Ming Jer Lee <mingjer@clpipe.dev>
License: MIT
License-File: LICENSE
Keywords: column-lineage,data-lineage,lineage,pipeline,sql,sqlglot
Classifier: Development Status :: 4 - Beta
Classifier: Intended Audience :: Developers
Classifier: License :: OSI Approved :: MIT License
Classifier: Programming Language :: Python :: 3
Classifier: Programming Language :: Python :: 3.10
Classifier: Programming Language :: Python :: 3.11
Classifier: Programming Language :: Python :: 3.12
Classifier: Programming Language :: Python :: 3.13
Classifier: Topic :: Database
Classifier: Topic :: Scientific/Engineering :: Information Analysis
Classifier: Topic :: Software Development :: Libraries :: Python Modules
Classifier: Topic :: Software Development :: Quality Assurance
Requires-Python: >=3.10
Requires-Dist: cloudpickle>=3.1.2
Requires-Dist: graphviz>=0.20.0
Requires-Dist: jinja2>=3.0.0
Requires-Dist: sqlglot>=28.0.0
Provides-Extra: airflow
Requires-Dist: apache-airflow<3.0.0,>=2.7.0; extra == 'airflow'
Provides-Extra: all
Requires-Dist: apache-airflow<3.0.0,>=2.7.0; extra == 'all'
Requires-Dist: langchain-core>=1.0.0; extra == 'all'
Requires-Dist: langchain-ollama>=1.0.0; extra == 'all'
Requires-Dist: langchain-openai>=0.3.0; extra == 'all'
Requires-Dist: langchain>=1.0.0; extra == 'all'
Requires-Dist: mcp>=1.0.0; extra == 'all'
Provides-Extra: build
Requires-Dist: build>=1.0.0; extra == 'build'
Requires-Dist: twine>=4.0.0; extra == 'build'
Provides-Extra: dev
Requires-Dist: duckdb>=0.9.0; extra == 'dev'
Requires-Dist: ipykernel>=6.0.0; extra == 'dev'
Requires-Dist: jinja2>=3.0.0; extra == 'dev'
Requires-Dist: langchain-core>=1.0.0; extra == 'dev'
Requires-Dist: langchain-ollama>=1.0.0; extra == 'dev'
Requires-Dist: langchain>=1.0.0; extra == 'dev'
Requires-Dist: nbclient>=0.7.0; extra == 'dev'
Requires-Dist: nbformat>=5.0.0; extra == 'dev'
Requires-Dist: numpy>=1.24.0; extra == 'dev'
Requires-Dist: pandas>=2.0.0; extra == 'dev'
Requires-Dist: pytest-cov>=4.0.0; extra == 'dev'
Requires-Dist: pytest>=7.0.0; extra == 'dev'
Requires-Dist: ruff>=0.6.0; extra == 'dev'
Requires-Dist: ty>=0.0.1a0; extra == 'dev'
Provides-Extra: examples
Requires-Dist: graphviz>=0.20.0; extra == 'examples'
Requires-Dist: pandas>=2.0.0; extra == 'examples'
Requires-Dist: streamlit>=1.28.0; extra == 'examples'
Provides-Extra: llm
Requires-Dist: langchain-core>=1.0.0; extra == 'llm'
Requires-Dist: langchain-ollama>=1.0.0; extra == 'llm'
Requires-Dist: langchain-openai>=0.3.0; extra == 'llm'
Requires-Dist: langchain>=1.0.0; extra == 'llm'
Provides-Extra: mcp
Requires-Dist: mcp>=1.0.0; extra == 'mcp'
Provides-Extra: templates
Requires-Dist: jinja2>=3.0.0; extra == 'templates'
